Metadata-Version: 2.1
Name: satisfactory-planner
Version: 0.0.1
Summary: Analyze data, find all recipes and more in the game of Satisfactory
Home-page: UNKNOWN
License:  DO WHAT THE FUCK YOU WANT TO PUBLIC LICENSE
Keywords: satisfactory,game,analysis,jupyter,supply-chain
Platform: UNKNOWN
Classifier: Programming Language :: Python :: 3
Classifier: Operating System :: OS Independent
Classifier: License :: Free for non-commercial use
License-File: LICENSE.md
